enum_mixins/__init__.py
enum_mixins-0.0.1.dist-info/LICENSE
enum_mixins-0.0.1.dist-info/METADATA
enum_mixins-0.0.1.dist-info/WHEEL
enum_mixins-0.0.1.dist-info/top_level.txt
enum_mixins-0.0.1.dist-info/RECORD
